camera_calibration_patterns/__init__.py
camera_calibration_patterns/__main__.py
camera_calibration_patterns/gen_pattern.py
camera_calibration_patterns/svgfig.py
camera_calibration_patterns-0.1.0.dist-info/LICENSE
camera_calibration_patterns-0.1.0.dist-info/METADATA
camera_calibration_patterns-0.1.0.dist-info/WHEEL
camera_calibration_patterns-0.1.0.dist-info/entry_points.txt
camera_calibration_patterns-0.1.0.dist-info/RECORD
