Metadata-Version: 2.3
Name: camera-calibration-patterns
Version: 0.1.0
Summary: Python package for generating camera calibration patterns (based on OpenCV script)
License: Apache-2.0
Author: Victor Kataev
Author-email: kataev.victor.1234@gmail.com
Requires-Python: >=3.11
Classifier: Programming Language :: Python :: 3 :: Only
Classifier: Programming Language :: Python :: 3.11
Requires-Dist: numpy (>=2.3.2,<3.0.0)
